[{"description":"Loss,Neutral","value":6.0606060606060606},{"description":"Win,Neutral","value":6.75990675990676},{"description":"Win,Abroad","value":13.51981351981352},{"description":"Loss,Home","value":12.82051282051282},{"description":"Loss,Abroad","value":20.745920745920746},{"description":"Win,Home","value":17.24941724941725},{"description":"Draw,Neutral","value":4.195804195804196},{"description":"Draw,Abroad","value":11.421911421911423},{"description":"Draw,Home","value":7.226107226107226}]