[{"versus":"Albania","gf_max":4,"ga_max":0},{"versus":"Alemania","gf_max":3,"ga_max":6},{"versus":"Angola","gf_max":1,"ga_max":0},{"versus":"Antillas Holandesas","gf_max":8,"ga_max":2},{"versus":"Arabia Saudí","gf_max":5,"ga_max":1},{"versus":"Argelia","gf_max":2,"ga_max":2},{"versus":"Argentina","gf_max":3,"ga_max":6},{"versus":"Australia","gf_max":3,"ga_max":3},{"versus":"Belenenses","gf_max":0,"ga_max":3},{"versus":"Bélgica","gf_max":3,"ga_max":3},{"versus":"Belice","gf_max":7,"ga_max":0},{"versus":"Bermudas","gf_max":5,"ga_max":2},{"versus":"Bielorrusia","gf_max":2,"ga_max":3},{"versus":"Bolivia","gf_max":5,"ga_max":3},{"versus":"Bosnia-Herzegovina","gf_max":2,"ga_max":1},{"versus":"Brasil","gf_max":4,"ga_max":5},{"versus":"Bulgaria","gf_max":3,"ga_max":3},{"versus":"Camérun","gf_max":1,"ga_max":0},{"versus":"Canadá","gf_max":8,"ga_max":2},{"versus":"Checoslovaquia","gf_max":3,"ga_max":2},{"versus":"Chile","gf_max":3,"ga_max":7},{"versus":"Colo-Colo","gf_max":4,"ga_max":3},{"versus":"Colombia","gf_max":2,"ga_max":3},{"versus":"Comunidad de Estados Independientes","gf_max":4,"ga_max":1},{"versus":"Congo RD","gf_max":2,"ga_max":1},{"versus":"Costa de Marfil","gf_max":4,"ga_max":1},{"versus":"Costa Rica","gf_max":7,"ga_max":3},{"versus":"Croacia","gf_max":3,"ga_max":3},{"versus":"Cruzeiro","gf_max":0,"ga_max":1},{"versus":"Cuba","gf_max":7,"ga_max":2},{"versus":"Curazao","gf_max":2,"ga_max":0},{"versus":"Dinamarca","gf_max":3,"ga_max":3},{"versus":"Dominica","gf_max":10,"ga_max":0},{"versus":"Ecuador","gf_max":4,"ga_max":2},{"versus":"Egipto","gf_max":3,"ga_max":2},{"versus":"El Salvador","gf_max":8,"ga_max":2},{"versus":"Elche","gf_max":3,"ga_max":3},{"versus":"Escocia","gf_max":1,"ga_max":0},{"versus":"Eslovaquia","gf_max":5,"ga_max":2},{"versus":"Eslovenia","gf_max":1,"ga_max":2},{"versus":"España","gf_max":1,"ga_max":7},{"versus":"Estados Unidos","gf_max":7,"ga_max":4},{"versus":"Estados Unidos Olímpica","gf_max":2,"ga_max":0},{"versus":"Estonia","gf_max":6,"ga_max":0},{"versus":"Finlandia","gf_max":4,"ga_max":2},{"versus":"Fiyi","gf_max":2,"ga_max":0},{"versus":"Francia","gf_max":2,"ga_max":4},{"versus":"Gales","gf_max":2,"ga_max":1},{"versus":"Gambia","gf_max":5,"ga_max":1},{"versus":"Ghana","gf_max":2,"ga_max":1},{"versus":"Grecia","gf_max":2,"ga_max":3},{"versus":"Guadalupe","gf_max":2,"ga_max":0},{"versus":"Guatemala","gf_max":5,"ga_max":3},{"versus":"Guyana","gf_max":5,"ga_max":1},{"versus":"Haití","gf_max":8,"ga_max":3},{"versus":"Holanda","gf_max":3,"ga_max":3},{"versus":"Honduras","gf_max":8,"ga_max":4},{"versus":"Hungría","gf_max":5,"ga_max":4},{"versus":"Independiente","gf_max":1,"ga_max":5},{"versus":"Inglaterra","gf_max":2,"ga_max":8},{"versus":"Irak","gf_max":1,"ga_max":0},{"versus":"Irán","gf_max":4,"ga_max":1},{"versus":"Irlanda del Norte","gf_max":3,"ga_max":4},{"versus":"Islandia","gf_max":3,"ga_max":1},{"versus":"Israel","gf_max":3,"ga_max":1},{"versus":"Italia","gf_max":2,"ga_max":5},{"versus":"Jamaica","gf_max":8,"ga_max":3},{"versus":"Japón","gf_max":2,"ga_max":3},{"versus":"Jordania","gf_max":0,"ga_max":0},{"versus":"Kuwait","gf_max":0,"ga_max":0},{"versus":"Líbano","gf_max":7,"ga_max":1},{"versus":"Liberia","gf_max":5,"ga_max":4},{"versus":"Libia","gf_max":1,"ga_max":3},{"versus":"Luxemburgo","gf_max":1,"ga_max":2},{"versus":"Marruecos","gf_max":1,"ga_max":2},{"versus":"Martinica","gf_max":9,"ga_max":2},{"versus":"Milan","gf_max":1,"ga_max":1},{"versus":"Millonarios","gf_max":3,"ga_max":1},{"versus":"Nacional","gf_max":1,"ga_max":9},{"versus":"Nicaragua","gf_max":4,"ga_max":0},{"versus":"Nigeria","gf_max":4,"ga_max":2},{"versus":"Noruega","gf_max":4,"ga_max":5},{"versus":"Nueva Zelanda","gf_max":5,"ga_max":4},{"versus":"País Basco","gf_max":8,"ga_max":6},{"versus":"Panamá","gf_max":7,"ga_max":2},{"versus":"Paraguay","gf_max":6,"ga_max":2},{"versus":"Perú","gf_max":4,"ga_max":3},{"versus":"Polonia","gf_max":5,"ga_max":3},{"versus":"Portugal","gf_max":2,"ga_max":2},{"versus":"RDP de Corea","gf_max":2,"ga_max":1},{"versus":"Rep. Democrática Alemana","gf_max":1,"ga_max":2},{"versus":"República Checa","gf_max":1,"ga_max":2},{"versus":"República de Corea","gf_max":4,"ga_max":4},{"versus":"República de Irlanda","gf_max":3,"ga_max":2},{"versus":"RP China","gf_max":3,"ga_max":2},{"versus":"RP China Olímpica","gf_max":0,"ga_max":0},{"versus":"Rumanía","gf_max":2,"ga_max":2},{"versus":"Rusia","gf_max":2,"ga_max":4},{"versus":"Senegal","gf_max":2,"ga_max":0},{"versus":"Serbia","gf_max":2,"ga_max":0},{"versus":"Sheffield United","gf_max":1,"ga_max":1},{"versus":"St. Kitts & Nevis","gf_max":8,"ga_max":0},{"versus":"St. Vincent","gf_max":11,"ga_max":1},{"versus":"Sudáfrica","gf_max":4,"ga_max":2},{"versus":"Suecia","gf_max":2,"ga_max":3},{"versus":"Suiza","gf_max":3,"ga_max":5},{"versus":"Surinam","gf_max":8,"ga_max":1},{"versus":"Tahití","gf_max":1,"ga_max":0},{"versus":"Trinidad & Tobago","gf_max":7,"ga_max":4},{"versus":"Túnez","gf_max":1,"ga_max":3},{"versus":"Ucrania","gf_max":2,"ga_max":1},{"versus":"Unión Soviética","gf_max":1,"ga_max":3},{"versus":"Univ. Católica","gf_max":1,"ga_max":5},{"versus":"Universidad de Chile","gf_max":2,"ga_max":1},{"versus":"Uruguay","gf_max":3,"ga_max":4},{"versus":"Venezuela","gf_max":4,"ga_max":3},{"versus":"Washington Diplomats","gf_max":0,"ga_max":3},{"versus":"Yemén","gf_max":2,"ga_max":0},{"versus":"Yugoslavia","gf_max":5,"ga_max":4}]