[{"versus":"Argentina","losses":21,"lossesAvg":0.12804878048780488},{"versus":"Colombia","losses":22,"lossesAvg":0.13414634146341464},{"versus":"Chile","losses":29,"lossesAvg":0.17682926829268292},{"versus":"Uruguay","losses":30,"lossesAvg":0.18292682926829268},{"versus":"México","losses":17,"lossesAvg":0.10365853658536585},{"versus":"Estados Unidos","losses":5,"lossesAvg":0.03048780487804878},{"versus":"Qatar","losses":1,"lossesAvg":0.006097560975609756},{"versus":"Perú","losses":20,"lossesAvg":0.12195121951219512},{"versus":"Brasil","losses":26,"lossesAvg":0.15853658536585366},{"versus":"Paraguay","losses":21,"lossesAvg":0.12804878048780488},{"versus":"Bolivia","losses":6,"lossesAvg":0.036585365853658534},{"versus":"Suiza","losses":1,"lossesAvg":0.006097560975609756},{"versus":"España","losses":2,"lossesAvg":0.012195121951219513},{"versus":"Alemania","losses":2,"lossesAvg":0.012195121951219513},{"versus":"Venezuela","losses":10,"lossesAvg":0.06097560975609756},{"versus":"República de Corea","losses":1,"lossesAvg":0.006097560975609756},{"versus":"El Salvador","losses":1,"lossesAvg":0.006097560975609756},{"versus":"Omán","losses":1,"lossesAvg":0.006097560975609756},{"versus":"Francia","losses":1,"lossesAvg":0.006097560975609756},{"versus":"Honduras","losses":2,"lossesAvg":0.012195121951219513},{"versus":"Inglaterra","losses":2,"lossesAvg":0.012195121951219513},{"versus":"Macedonia FYR","losses":1,"lossesAvg":0.006097560975609756},{"versus":"Japón","losses":2,"lossesAvg":0.012195121951219513},{"versus":"Holanda","losses":1,"lossesAvg":0.006097560975609756},{"versus":"Uganda","losses":1,"lossesAvg":0.006097560975609756},{"versus":"Senegal","losses":2,"lossesAvg":0.012195121951219513},{"versus":"Polonia","losses":1,"lossesAvg":0.006097560975609756},{"versus":"Jordania","losses":1,"lossesAvg":0.006097560975609756},{"versus":"Cataluña","losses":1,"lossesAvg":0.006097560975609756},{"versus":"Italia","losses":1,"lossesAvg":0.006097560975609756},{"versus":"Haití","losses":2,"lossesAvg":0.012195121951219513},{"versus":"Líbano","losses":1,"lossesAvg":0.006097560975609756},{"versus":"Escocia","losses":1,"lossesAvg":0.006097560975609756},{"versus":"Costa Rica","losses":2,"lossesAvg":0.012195121951219513},{"versus":"Cuba","losses":2,"lossesAvg":0.012195121951219513},{"versus":"Rep. Democrática Alemana","losses":1,"lossesAvg":0.006097560975609756},{"versus":"Guatemala","losses":1,"lossesAvg":0.006097560975609756},{"versus":"Bulgaria","losses":1,"lossesAvg":0.006097560975609756},{"versus":"República de Irlanda","losses":1,"lossesAvg":0.006097560975609756},{"versus":"Portugal","losses":1,"lossesAvg":0.006097560975609756},{"versus":"Millonarios","losses":2,"lossesAvg":0.012195121951219513}]