[{"versus":"Perú","matches":57,"gf_sum":67,"ga_sum":60},{"versus":"Ecuador","matches":46,"gf_sum":53,"ga_sum":44},{"versus":"Uruguay","matches":43,"gf_sum":47,"ga_sum":64},{"versus":"Chile","matches":41,"gf_sum":52,"ga_sum":69},{"versus":"Venezuela","matches":39,"gf_sum":53,"ga_sum":24},{"versus":"Argelia","matches":1,"gf_sum":0,"ga_sum":3},{"versus":"Brasil","matches":32,"gf_sum":17,"ga_sum":64},{"versus":"Paraguay","matches":46,"gf_sum":55,"ga_sum":51},{"versus":"Qatar","matches":1,"gf_sum":1,"ga_sum":0},{"versus":"Argentina","matches":37,"gf_sum":36,"ga_sum":67},{"versus":"Panamá","matches":4,"gf_sum":9,"ga_sum":4},{"versus":"República de Corea","matches":7,"gf_sum":7,"ga_sum":12},{"versus":"Japón","matches":5,"gf_sum":7,"ga_sum":3},{"versus":"Costa Rica","matches":11,"gf_sum":25,"ga_sum":12},{"versus":"Estados Unidos","matches":20,"gf_sum":28,"ga_sum":14},{"versus":"Inglaterra","matches":6,"gf_sum":4,"ga_sum":11},{"versus":"Senegal","matches":3,"gf_sum":5,"ga_sum":2},{"versus":"Polonia","matches":6,"gf_sum":10,"ga_sum":8},{"versus":"Egipto","matches":2,"gf_sum":1,"ga_sum":1},{"versus":"Australia","matches":4,"gf_sum":4,"ga_sum":2},{"versus":"Francia","matches":4,"gf_sum":5,"ga_sum":7},{"versus":"RP China","matches":2,"gf_sum":5,"ga_sum":2},{"versus":"Camérun","matches":4,"gf_sum":8,"ga_sum":3},{"versus":"España","matches":3,"gf_sum":3,"ga_sum":4},{"versus":"Bolivia","matches":29,"gf_sum":44,"ga_sum":29},{"versus":"Haití","matches":5,"gf_sum":12,"ga_sum":4},{"versus":"Kuwait","matches":1,"gf_sum":3,"ga_sum":1},{"versus":"Bahrein","matches":1,"gf_sum":6,"ga_sum":0},{"versus":"Eslovenia","matches":1,"gf_sum":1,"ga_sum":0},{"versus":"Canadá","matches":3,"gf_sum":4,"ga_sum":2},{"versus":"El Salvador","matches":7,"gf_sum":14,"ga_sum":5},{"versus":"Costa de Marfil","matches":1,"gf_sum":2,"ga_sum":1},{"versus":"Grecia","matches":2,"gf_sum":5,"ga_sum":0},{"versus":"Jordania","matches":1,"gf_sum":3,"ga_sum":0},{"versus":"Túnez","matches":2,"gf_sum":2,"ga_sum":1},{"versus":"Holanda","matches":1,"gf_sum":0,"ga_sum":0},{"versus":"Bélgica","matches":2,"gf_sum":2,"ga_sum":2},{"versus":"Serbia","matches":1,"gf_sum":1,"ga_sum":0},{"versus":"Guatemala","matches":3,"gf_sum":6,"ga_sum":3},{"versus":"Guyana","matches":1,"gf_sum":7,"ga_sum":1},{"versus":"México","matches":25,"gf_sum":20,"ga_sum":22},{"versus":"Jamaica","matches":5,"gf_sum":7,"ga_sum":1},{"versus":"Honduras","matches":13,"gf_sum":11,"ga_sum":11},{"versus":"Nigeria","matches":4,"gf_sum":4,"ga_sum":1},{"versus":"Sudáfrica","matches":1,"gf_sum":1,"ga_sum":2},{"versus":"Cataluña","matches":1,"gf_sum":1,"ga_sum":2},{"versus":"República de Irlanda","matches":1,"gf_sum":0,"ga_sum":1},{"versus":"Montenegro","matches":1,"gf_sum":1,"ga_sum":0},{"versus":"Suiza","matches":4,"gf_sum":9,"ga_sum":6},{"versus":"Marruecos","matches":1,"gf_sum":2,"ga_sum":0},{"versus":"Alemania","matches":4,"gf_sum":5,"ga_sum":10},{"versus":"Rumanía","matches":3,"gf_sum":1,"ga_sum":4},{"versus":"Trinidad & Tobago","matches":3,"gf_sum":8,"ga_sum":4},{"versus":"Eslovaquia","matches":3,"gf_sum":2,"ga_sum":0},{"versus":"Turquía","matches":1,"gf_sum":1,"ga_sum":2},{"versus":"Nueva Zelanda","matches":1,"gf_sum":3,"ga_sum":1},{"versus":"Liberia","matches":1,"gf_sum":2,"ga_sum":1},{"versus":"Escocia","matches":3,"gf_sum":3,"ga_sum":2},{"versus":"Yugoslavia","matches":4,"gf_sum":0,"ga_sum":7},{"versus":"Noruega","matches":1,"gf_sum":0,"ga_sum":0},{"versus":"Hong Kong","matches":1,"gf_sum":3,"ga_sum":1},{"versus":"Irlanda del Norte","matches":1,"gf_sum":2,"ga_sum":0},{"versus":"Suecia","matches":2,"gf_sum":2,"ga_sum":2},{"versus":"Arabia Saudí","matches":2,"gf_sum":2,"ga_sum":1},{"versus":"Emiratos Árabes Uni.","matches":1,"gf_sum":2,"ga_sum":0},{"versus":"Hungría","matches":1,"gf_sum":1,"ga_sum":3},{"versus":"Unión Soviética","matches":3,"gf_sum":5,"ga_sum":7},{"versus":"Israel","matches":2,"gf_sum":1,"ga_sum":0},{"versus":"Millonarios","matches":1,"gf_sum":1,"ga_sum":2},{"versus":"Finlandia","matches":1,"gf_sum":3,"ga_sum":1},{"versus":"Atlético Mineiro","matches":1,"gf_sum":1,"ga_sum":6},{"versus":"Real Madrid","matches":2,"gf_sum":1,"ga_sum":1},{"versus":"Rep. Democrática Alemana","matches":1,"gf_sum":0,"ga_sum":2},{"versus":"CAF XI","matches":1,"gf_sum":0,"ga_sum":3},{"versus":"CONCACAF XI","matches":1,"gf_sum":4,"ga_sum":3},{"versus":"Santiago Morning","matches":1,"gf_sum":2,"ga_sum":7}]